nikhil_tools/__init__.py
nikhil_tools/ble_scanner.py
nikhil_tools/cli.py
nikhil_tools/dashboard.py
nikhil_tools/ip_scanner.py
nikhil_tools/speed_test.py
nikhil_tools/system_monitor.py
nikhil_tools/wifi_scanner.py
nikhil_tools-0.4.1.dist-info/licenses/LICENSE
nikhil_tools-0.4.1.dist-info/METADATA
nikhil_tools-0.4.1.dist-info/WHEEL
nikhil_tools-0.4.1.dist-info/entry_points.txt
nikhil_tools-0.4.1.dist-info/top_level.txt
nikhil_tools-0.4.1.dist-info/RECORD
