Metadata-Version: 2.4
Name: nikhil-tools
Version: 0.4.1
Summary: Python toolkit with BLE, WiFi, IP scanning and system monitoring utilities.
Author: Nikhil Deepak
License-Expression: MIT
Keywords: scanner,network,bluetooth,wifi,system-monitor,utilities
Classifier: Development Status :: 4 - Beta
Classifier: Intended Audience :: Developers
Classifier: Programming Language :: Python :: 3
Classifier: Programming Language :: Python :: 3.9
Classifier: Programming Language :: Python :: 3.10
Classifier: Programming Language :: Python :: 3.11
Classifier: Programming Language :: Python :: 3.12
Classifier: Operating System :: MacOS
Classifier: Operating System :: Microsoft :: Windows
Classifier: Operating System :: POSIX :: Linux
Requires-Python: >=3.9
License-File: LICENSE
Requires-Dist: bleak>=0.21
Requires-Dist: psutil>=5.9
Requires-Dist: pyobjc-framework-CoreWLAN>=9.0; sys_platform == "darwin"
Requires-Dist: pyobjc-framework-CoreBluetooth>=9.0; sys_platform == "darwin"
Provides-Extra: dev
Requires-Dist: pytest>=8.3; extra == "dev"
Dynamic: license-file
